{"wantWatch":[],"watching":[{"title":"家庭教师HITMAN REBORN!","type":"番剧","area":"日本","cover":"https://i0.hdslb.com/bfs/bangumi/e46cc26d95a6b09541a8bda484f041eebb474c1a.png","totalCount":"全203话","id":1376,"follow":"203.9 万","view":"1.9 亿","danmaku":"405.6 万","coin":"36.7 万","score":9.9,"des":"本片是围绕彭格列第十代首领泽田纲吉与其家族成员的成长而展开的。彭格列初代后裔泽田纲吉是一个做什么都不行的“废柴纲”，但是为了培养成为彭格列家族首领，从意大利来了的里包恩负责教导纲吉。内心善良的他不愿意..."},{"title":"奇幻世界舅舅","type":"番剧","area":"日本","cover":"https://i0.hdslb.com/bfs/bangumi/image/7edad1244ad72416dd576866e0513665f2fc9f40.png","totalCount":"全13话","id":28338491,"follow":"212.1 万","view":"1.1 亿","danmaku":"28.1 万","coin":"37.7 万","score":9.8,"des":"2017年秋天――\n\n17岁时被卡车撞到，\n并在此后17年间昏睡不醒的舅舅醒了。\n前往病房探望的外甥敬文看到的是，口中嘟囔着莫名其妙的话语，\n从奇幻世界「格兰巴哈马尔」回到现实世界的舅舅。\n\n……舅舅..."},{"title":"我独自升级","type":"番剧","area":"日本","cover":"https://i0.hdslb.com/bfs/bangumi/image/3a3eb31610713c19bed556fa915a2b7776d8c85d.png","totalCount":"全12话","id":21194555,"follow":"51.1 万","view":"1784.3 万","danmaku":"2.7 万","coin":"4.0 万","score":8.9,"des":"自从连接异次元与当前世界的通道“门”突然出现后已过去十余年，\n世界上出现了被称为“猎人”的，觉醒了非凡力量的人们。\n猎人在门内攻略地下城以获取回报以维持生计，\n但在强者如云的猎人中，「水篠旬」作为被称..."},{"title":"干物妹！小埋","type":"番剧","area":"日本","cover":"https://i0.hdslb.com/bfs/bangumi/image/e7fb0d62e99b974e00e19b68e51e8b1fcdfc02d5.png","totalCount":"全12话","id":2580,"follow":"526.1 万","view":"2.0 亿","danmaku":"619.5 万","coin":"50.0 万","score":9.3,"des":"我的妹妹小埋16岁，完美的妹妹，完美的高中生，但在家里却是个超懒的干物妹。\n然而妹妹在家的一切她生活中的朋友并不知道，居住在同一栋楼的天然少女，以及无意间来到我家的冷酷少女，她们会发现小埋的真实面目吗..."},{"title":"名侦探柯南 沉默的15分钟","type":"番剧","area":"日本","cover":"https://i0.hdslb.com/bfs/bangumi/image/8762468347f06d5a46bdd50a446e0bc535909361.jpg","totalCount":"全1话","id":28228957,"follow":"22.2 万","view":"964.4 万","danmaku":"12.5 万","coin":"2.1 万","score":8.9,"des":"朝仓都知事收到一封神秘的恐吓信，内容为：“对于你那4年执政中桀骜不驯的态度，上天将给予惩罚！”。隔天，由都知事主导开通的新地下铁隧道遭到炸毁。虽然多亏柯南知道恐吓信而使得这次爆破事件没有人员伤亡，但是..."},{"title":"鲁邦三世VS名侦探柯南THE MOVIE","type":"番剧","area":"日本","cover":"https://i0.hdslb.com/bfs/bangumi/image/df0c8e7c1df58b9303b0f27db6b50a5aea354385.png","totalCount":"全1话","id":28228777,"follow":"61.6 万","view":"932.0 万","danmaku":"11.7 万","coin":"3.3 万","score":9.7,"des":"没有月光的漆黑之夜，警方收到了一封针对由米花町的银行保管的樱桃蓝宝石的预告函。\n那个发件人，竟是大盗——鲁邦三世？！鲁邦的专职调查官、ICPO（国际刑事警察组织）的钱形警部，与警视厅的目暮警部搭档，集..."},{"title":"博人传 火影忍者新时代","type":"番剧","area":"日本","cover":"https://i0.hdslb.com/bfs/bangumi/image/71d54cae830d32a5af776dcc46632146fbdba868.jpg","totalCount":"全72话","id":5978,"follow":"227.7 万","view":"3832.2 万","danmaku":"15.7 万","coin":"4.2 万","score":4.5,"des":"随着和平的到来而走向近代化的木叶隐村。高楼林立，巨大显示屏中播放出影像，连结各区域的电车在村里奔驰。虽说是忍者村，但一般民众也增多，忍者的生存方式也在逐渐改变的这个时代——\n村子的领袖、第七代火影·漩..."}],"watched":[]}